Workbook

Sheet Projet
B2: Capital inital disponible | C2: 200000
B3: Enveloppe globale mensuelle pour logement + épargne | C3: 3400 | D3: =IF(C3<G3,"WARNING ! Veuillez augmenter votre enveloppe globale mensuelle du projet","") | F3: Coût total mensualisé propriétaire | G3: =FLux_Achat_RP!H3/12 -> 2633.9134
B5: Prix net vendeur | C5: 420000 | F5: Mensualité (crédit + assurance) | G5: =Amortissement_prêt!H8 -> 2384.719 | I5: Patrimoine 5 ans | K5: Patrimoine 10 ans | M5: Patrimoine 20 ans
B6: Frais de notaire | C6: =(MIN(C5,6500)*3.87%+MAX(MIN(C5,17000)-6500,0)*1.596%+MAX(MIN(C5,60000)-17000,0)*1.064%+MAX(C5-60000,0)*0.799%)*1.2 +C5*IF(D6="Neuf",0.71498%,5.80665%) +C5*0.1% +1200 -> 30511.59 | D6: Ancien | F6: GAP des mensualités vs le loyer locataire | G6: =Amortissement_prêt!H8-Bilan_Revente!O4/12 -> 784.71903 | I6: Achat | J6: =Bilan_Revente!N8 -> 367111.73 | K6: Achat | L6: =Bilan_Revente!N13 -> 567218.17 | M6: Achat | N6: =Bilan_Revente!N23 -> 1088531.5
B7: Frais d'agence | C7: 0 | F7: Epargne mensuelle investie par les locataires(an 1) | G7: =Bilan_Revente!P4/12 -> 1800 | I7: Location | J7: =Bilan_Revente!T8 -> 372571.74 | K7: Location | L7: =Bilan_Revente!T13 -> 587306.14 | M7: Location | N7: =Bilan_Revente!T23 -> 1191858.8
B8: Travaux | C8: 50000 | F8: Epargne mensuelle investie par les propriétaire (an 1) | G8: =Bilan_Revente!G4/12 -> 766.08656
B9: Frais d'acquisition bancaire | C9: 2000
B10: COUTS D'ACQUISITION PROJET | C10: =SUM(C5:C9) -> 502511.59
B12: Valeur réelle estimée du bien à l'achat en année 0 post-travaux | C12: 500000
B14: Apport | C14: 100000
B15: Dettes | C15: =C10-C14 -> 402511.59
B16: Durée | C16: 20
B17: Taux | C17: 0.035
B18: Assurance emprunteur | C18: 0.0015
B20: Charges de copro annuelles | C20: 1500
B21: Taxe foncière | C21: 1500
B22: Revalorisation annuelle du bien | C22: 0.01
B23: Revalorisation annuelle Taxe foncière | C23: 0.01
B24: Revalorisation annuelle charges copro | C24: 0.01
B26: Loyer en tant que locataire | C26: 1600
B27: Revalorisation annuelle des loyers en tant que locataire | C27: 0.01
B28: Rendement brut en bourse | C28: 0.05
B29: Fiscalité sur les plus-values à la sortie | C29: 0.314

Sheet Amortissement_prêt
B1: Capital emprunté | C1: =Projet!C15 -> 402511.59
B2: Taux de crédit annuel | C2: =Projet!C17 -> 0.035
B3: Durée (année) | C3: =Projet!C16 -> 20
B4: Taux assurance annuel | C4: =Projet!C18 -> 0.0015
B5: Mensualité de crédit fixe | C5: =-PMT(C2/12,C3*12,C1) -> 2334.4051
A7: Mois | B7: CRD début de mois | C7: Mensualité de crédit | D7: Intérêt du mois | E7: Capital amorti | F7: CRD fin de mois | G7: Assurance du mois | H7: Mensualité totale
A8: 1 | B8: =C1 -> 402511.59 | C8: =IF(A8<=$C$3*12,$C$5,0) -> 2334.4051 | D8: =B8*$C$2/12 -> 1173.9921 | E8: =IF(C8-D8<0,0,C8-D8) -> 1160.4129 | F8: =MAX(B8-E8,0) -> 401351.18 | G8: =IF(A8<=$C$3*12,B8*$C$4/12,0) -> 50.313949 | H8: =C8+G8 -> 2384.719
A9: =A8+1 -> 2 | B9: =F8 -> 401351.18 | C9: =IF(A9<=$C$3*12,$C$5,0) -> 2334.4051 | D9: =B9*$C$2/12 -> 1170.6076 | E9: =IF(C9-D9<0,0,C9-D9) -> 1163.7975 | F9: =MAX(B9-E9,0) -> 400187.38 | G9: =IF(A9<=$C$3*12,B9*$C$4/12,0) -> 50.168897 | H9: =C9+G9 -> 2384.574
A10: =A9+1 -> 3 | B10: =F9 -> 400187.38 | C10: =IF(A10<=$C$3*12,$C$5,0) -> 2334.4051 | D10: =B10*$C$2/12 -> 1167.2132 | E10: =IF(C10-D10<0,0,C10-D10) -> 1167.1919 | F10: =MAX(B10-E10,0) -> 399020.19 | G10: =IF(A10<=$C$3*12,B10*$C$4/12,0) -> 50.023422 | H10: =C10+G10 -> 2384.4285
A11: =A10+1 -> 4 | B11: =F10 -> 399020.19 | C11: =IF(A11<=$C$3*12,$C$5,0) -> 2334.4051 | D11: =B11*$C$2/12 -> 1163.8089 | E11: =IF(C11-D11<0,0,C11-D11) -> 1170.5962 | F11: =MAX(B11-E11,0) -> 397849.59 | G11: =IF(A11<=$C$3*12,B11*$C$4/12,0) -> 49.877523 | H11: =C11+G11 -> 2384.2826
A12: =A11+1 -> 5 | B12: =F11 -> 397849.59 | C12: =IF(A12<=$C$3*12,$C$5,0) -> 2334.4051 | D12: =B12*$C$2/12 -> 1160.3946 | E12: =IF(C12-D12<0,0,C12-D12) -> 1174.0104 | F12: =MAX(B12-E12,0) -> 396675.58 | G12: =IF(A12<=$C$3*12,B12*$C$4/12,0) -> 49.731199 | H12: =C12+G12 -> 2384.1363
A13: =A12+1 -> 6 | B13: =F12 -> 396675.58 | C13: =IF(A13<=$C$3*12,$C$5,0) -> 2334.4051 | D13: =B13*$C$2/12 -> 1156.9704 | E13: =IF(C13-D13<0,0,C13-D13) -> 1177.4346 | F13: =MAX(B13-E13,0) -> 395498.15 | G13: =IF(A13<=$C$3*12,B13*$C$4/12,0) -> 49.584448 | H13: =C13+G13 -> 2383.9895
A14: =A13+1 -> 7 | B14: =F13 -> 395498.15 | C14: =IF(A14<=$C$3*12,$C$5,0) -> 2334.4051 | D14: =B14*$C$2/12 -> 1153.5363 | E14: =IF(C14-D14<0,0,C14-D14) -> 1180.8688 | F14: =MAX(B14-E14,0) -> 394317.28 | G14: =IF(A14<=$C$3*12,B14*$C$4/12,0) -> 49.437268 | H14: =C14+G14 -> 2383.8424
A15: =A14+1 -> 8 | B15: =F14 -> 394317.28 | C15: =IF(A15<=$C$3*12,$C$5,0) -> 2334.4051 | D15: =B15*$C$2/12 -> 1150.0921 | E15: =IF(C15-D15<0,0,C15-D15) -> 1184.313 | F15: =MAX(B15-E15,0) -> 393132.96 | G15: =IF(A15<=$C$3*12,B15*$C$4/12,0) -> 49.28966 | H15: =C15+G15 -> 2383.6947
A16: =A15+1 -> 9 | B16: =F15 -> 393132.96 | C16: =IF(A16<=$C$3*12,$C$5,0) -> 2334.4051 | D16: =B16*$C$2/12 -> 1146.6378 | E16: =IF(C16-D16<0,0,C16-D16) -> 1187.7673 | F16: =MAX(B16-E16,0) -> 391945.2 | G16: =IF(A16<=$C$3*12,B16*$C$4/12,0) -> 49.141621 | H16: =C16+G16 -> 2383.5467
A17: =A16+1 -> 10 | B17: =F16 -> 391945.2 | C17: =IF(A17<=$C$3*12,$C$5,0) -> 2334.4051 | D17: =B17*$C$2/12 -> 1143.1735 | E17: =IF(C17-D17<0,0,C17-D17) -> 1191.2316 | F17: =MAX(B17-E17,0) -> 390753.97 | G17: =IF(A17<=$C$3*12,B17*$C$4/12,0) -> 48.99315 | H17: =C17+G17 -> 2383.3982
A18: =A17+1 -> 11 | B18: =F17 -> 390753.97 | C18: =IF(A18<=$C$3*12,$C$5,0) -> 2334.4051 | D18: =B18*$C$2/12 -> 1139.6991 | E18: =IF(C18-D18<0,0,C18-D18) -> 1194.706 | F18: =MAX(B18-E18,0) -> 389559.26 | G18: =IF(A18<=$C$3*12,B18*$C$4/12,0) -> 48.844246 | H18: =C18+G18 -> 2383.2493
A19: =A18+1 -> 12 | B19: =F18 -> 389559.26 | C19: =IF(A19<=$C$3*12,$C$5,0) -> 2334.4051 | D19: =B19*$C$2/12 -> 1136.2145 | E19: =IF(C19-D19<0,0,C19-D19) -> 1198.1906 | F19: =MAX(B19-E19,0) -> 388361.07 | G19: =IF(A19<=$C$3*12,B19*$C$4/12,0) -> 48.694907 | H19: =C19+G19 -> 2383.1
A20: =A19+1 -> 13 | B20: =F19 -> 388361.07 | C20: =IF(A20<=$C$3*12,$C$5,0) -> 2334.4051 | D20: =B20*$C$2/12 -> 1132.7198 | E20: =IF(C20-D20<0,0,C20-D20) -> 1201.6853 | F20: =MAX(B20-E20,0) -> 387159.38 | G20: =IF(A20<=$C$3*12,B20*$C$4/12,0) -> 48.545134 | H20: =C20+G20 -> 2382.9502
... A307: =A306+1 -> 300 | B307: =F306 -> 6.5028871e-11 | C307: =IF(A307<=$C$3*12,$C$5,0) -> 0 | D307: =B307*$C$2/12 -> 1.8966754e-13 | E307: =IF(C307-D307<0,0,C307-D307) -> 0 | F307: =MAX(B307-E307,0) -> 6.5028871e-11 | G307: =IF(A307<=$C$3*12,B307*$C$4/12,0) -> 0 | H307: =C307+G307 -> 0

Sheet Amortissement_annuel_prêt
B8: CRD fin d'année | C8: Intérêts payés dans l'année | D8: Capital amorti dans l'année | E8: Assurance payée dans l'année | F8: Total payé dans l'annéee
A9: 1 | B9: {=INDEX(Amortissement_prêt!$F$8:$F$307,A9*12)} -> 388361.07 | C9: =SUMIFS(Amortissement_prêt!$D$8:$D$307,Amortissement_prêt!$A$8:$A$307,">"&(A9-1)*12,Amortissement_prêt!$A$8:$A$307,"<="&A9*12) -> 13862.34 | D9: =SUMIFS(Amortissement_prêt!$E$8:$E$307,Amortissement_prêt!$A$8:$A$307,">"&(A9-1)*12,Amortissement_prêt!$A$8:$A$307,"<="&A9*12) -> 14150.521 | E9: =SUMIFS(Amortissement_prêt!$G$8:$G$307,Amortissement_prêt!$A$8:$A$307,">"&(A9-1)*12,Amortissement_prêt!$A$8:$A$307,"<="&A9*12) -> 594.10029 | F9: =C9+D9+E9 -> 28606.961
A10: 2 | B10: {=INDEX(Amortissement_prêt!$F$8:$F$307,A10*12)} -> 373707.26 | C10: =SUMIFS(Amortissement_prêt!$D$8:$D$307,Amortissement_prêt!$A$8:$A$307,">"&(A10-1)*12,Amortissement_prêt!$A$8:$A$307,"<="&A10*12) -> 13359.049 | D10: =SUMIFS(Amortissement_prêt!$E$8:$E$307,Amortissement_prêt!$A$8:$A$307,">"&(A10-1)*12,Amortissement_prêt!$A$8:$A$307,"<="&A10*12) -> 14653.812 | E10: =SUMIFS(Amortissement_prêt!$G$8:$G$307,Amortissement_prêt!$A$8:$A$307,">"&(A10-1)*12,Amortissement_prêt!$A$8:$A$307,"<="&A10*12) -> 572.53068 | F10: =C10+D10+E10 -> 28585.392
A11: 3 | B11: {=INDEX(Amortissement_prêt!$F$8:$F$307,A11*12)} -> 358532.25 | C11: =SUMIFS(Amortissement_prêt!$D$8:$D$307,Amortissement_prêt!$A$8:$A$307,">"&(A11-1)*12,Amortissement_prêt!$A$8:$A$307,"<="&A11*12) -> 12837.858 | D11: =SUMIFS(Amortissement_prêt!$E$8:$E$307,Amortissement_prêt!$A$8:$A$307,">"&(A11-1)*12,Amortissement_prêt!$A$8:$A$307,"<="&A11*12) -> 15175.003 | E11: =SUMIFS(Amortissement_prêt!$G$8:$G$307,Amortissement_prêt!$A$8:$A$307,">"&(A11-1)*12,Amortissement_prêt!$A$8:$A$307,"<="&A11*12) -> 550.1939 | F11: =C11+D11+E11 -> 28563.055
A12: 4 | B12: {=INDEX(Amortissement_prêt!$F$8:$F$307,A12*12)} -> 342817.52 | C12: =SUMIFS(Amortissement_prêt!$D$8:$D$307,Amortissement_prêt!$A$8:$A$307,">"&(A12-1)*12,Amortissement_prêt!$A$8:$A$307,"<="&A12*12) -> 12298.129 | D12: =SUMIFS(Amortissement_prêt!$E$8:$E$307,Amortissement_prêt!$A$8:$A$307,">"&(A12-1)*12,Amortissement_prêt!$A$8:$A$307,"<="&A12*12) -> 15714.732 | E12: =SUMIFS(Amortissement_prêt!$G$8:$G$307,Amortissement_prêt!$A$8:$A$307,">"&(A12-1)*12,Amortissement_prêt!$A$8:$A$307,"<="&A12*12) -> 527.06268 | F12: =C12+D12+E12 -> 28539.924
A13: 5 | B13: {=INDEX(Amortissement_prêt!$F$8:$F$307,A13*12)} -> 326543.87 | C13: =SUMIFS(Amortissement_prêt!$D$8:$D$307,Amortissement_prêt!$A$8:$A$307,">"&(A13-1)*12,Amortissement_prêt!$A$8:$A$307,"<="&A13*12) -> 11739.204 | D13: =SUMIFS(Amortissement_prêt!$E$8:$E$307,Amortissement_prêt!$A$8:$A$307,">"&(A13-1)*12,Amortissement_prêt!$A$8:$A$307,"<="&A13*12) -> 16273.657 | E13: =SUMIFS(Amortissement_prêt!$G$8:$G$307,Amortissement_prêt!$A$8:$A$307,">"&(A13-1)*12,Amortissement_prêt!$A$8:$A$307,"<="&A13*12) -> 503.10874 | F13: =C13+D13+E13 -> 28515.97
A14: 6 | B14: {=INDEX(Amortissement_prêt!$F$8:$F$307,A14*12)} -> 309691.4 | C14: =SUMIFS(Amortissement_prêt!$D$8:$D$307,Amortissement_prêt!$A$8:$A$307,">"&(A14-1)*12,Amortissement_prêt!$A$8:$A$307,"<="&A14*12) -> 11160.4 | D14: =SUMIFS(Amortissement_prêt!$E$8:$E$307,Amortissement_prêt!$A$8:$A$307,">"&(A14-1)*12,Amortissement_prêt!$A$8:$A$307,"<="&A14*12) -> 16852.461 | E14: =SUMIFS(Amortissement_prêt!$G$8:$G$307,Amortissement_prêt!$A$8:$A$307,">"&(A14-1)*12,Amortissement_prêt!$A$8:$A$307,"<="&A14*12) -> 478.30284 | F14: =C14+D14+E14 -> 28491.164
A15: 7 | B15: {=INDEX(Amortissement_prêt!$F$8:$F$307,A15*12)} -> 292239.55 | C15: =SUMIFS(Amortissement_prêt!$D$8:$D$307,Amortissement_prêt!$A$8:$A$307,">"&(A15-1)*12,Amortissement_prêt!$A$8:$A$307,"<="&A15*12) -> 10561.009 | D15: =SUMIFS(Amortissement_prêt!$E$8:$E$307,Amortissement_prêt!$A$8:$A$307,">"&(A15-1)*12,Amortissement_prêt!$A$8:$A$307,"<="&A15*12) -> 17451.852 | E15: =SUMIFS(Amortissement_prêt!$G$8:$G$307,Amortissement_prêt!$A$8:$A$307,">"&(A15-1)*12,Amortissement_prêt!$A$8:$A$307,"<="&A15*12) -> 452.61467 | F15: =C15+D15+E15 -> 28465.476
A16: 8 | B16: {=INDEX(Amortissement_prêt!$F$8:$F$307,A16*12)} -> 274166.99 | C16: =SUMIFS(Amortissement_prêt!$D$8:$D$307,Amortissement_prêt!$A$8:$A$307,">"&(A16-1)*12,Amortissement_prêt!$A$8:$A$307,"<="&A16*12) -> 9940.2997 | D16: =SUMIFS(Amortissement_prêt!$E$8:$E$307,Amortissement_prêt!$A$8:$A$307,">"&(A16-1)*12,Amortissement_prêt!$A$8:$A$307,"<="&A16*12) -> 18072.561 | E16: =SUMIFS(Amortissement_prêt!$G$8:$G$307,Amortissement_prêt!$A$8:$A$307,">"&(A16-1)*12,Amortissement_prêt!$A$8:$A$307,"<="&A16*12) -> 426.01284 | F16: =C16+D16+E16 -> 28438.874
A17: 9 | B17: {=INDEX(Amortissement_prêt!$F$8:$F$307,A17*12)} -> 255451.64 | C17: =SUMIFS(Amortissement_prêt!$D$8:$D$307,Amortissement_prêt!$A$8:$A$307,">"&(A17-1)*12,Amortissement_prêt!$A$8:$A$307,"<="&A17*12) -> 9297.5138 | D17: =SUMIFS(Amortissement_prêt!$E$8:$E$307,Amortissement_prêt!$A$8:$A$307,">"&(A17-1)*12,Amortissement_prêt!$A$8:$A$307,"<="&A17*12) -> 18715.347 | E17: =SUMIFS(Amortissement_prêt!$G$8:$G$307,Amortissement_prêt!$A$8:$A$307,">"&(A17-1)*12,Amortissement_prêt!$A$8:$A$307,"<="&A17*12) -> 398.46488 | F17: =C17+D17+E17 -> 28411.326
A18: 10 | B18: {=INDEX(Amortissement_prêt!$F$8:$F$307,A18*12)} -> 236070.65 | C18: =SUMIFS(Amortissement_prêt!$D$8:$D$307,Amortissement_prêt!$A$8:$A$307,">"&(A18-1)*12,Amortissement_prêt!$A$8:$A$307,"<="&A18*12) -> 8631.8659 | D18: =SUMIFS(Amortissement_prêt!$E$8:$E$307,Amortissement_prêt!$A$8:$A$307,">"&(A18-1)*12,Amortissement_prêt!$A$8:$A$307,"<="&A18*12) -> 19380.995 | E18: =SUMIFS(Amortissement_prêt!$G$8:$G$307,Amortissement_prêt!$A$8:$A$307,">"&(A18-1)*12,Amortissement_prêt!$A$8:$A$307,"<="&A18*12) -> 369.93711 | F18: =C18+D18+E18 -> 28382.798
A19: 11 | B19: {=INDEX(Amortissement_prêt!$F$8:$F$307,A19*12)} -> 216000.33 | C19: =SUMIFS(Amortissement_prêt!$D$8:$D$307,Amortissement_prêt!$A$8:$A$307,">"&(A19-1)*12,Amortissement_prêt!$A$8:$A$307,"<="&A19*12) -> 7942.5429 | D19: =SUMIFS(Amortissement_prêt!$E$8:$E$307,Amortissement_prêt!$A$8:$A$307,">"&(A19-1)*12,Amortissement_prêt!$A$8:$A$307,"<="&A19*12) -> 20070.318 | E19: =SUMIFS(Amortissement_prêt!$G$8:$G$307,Amortissement_prêt!$A$8:$A$307,">"&(A19-1)*12,Amortissement_prêt!$A$8:$A$307,"<="&A19*12) -> 340.3947 | F19: =C19+D19+E19 -> 28353.256
A20: 12 | B20: {=INDEX(Amortissement_prêt!$F$8:$F$307,A20*12)} -> 195216.17 | C20: =SUMIFS(Amortissement_prêt!$D$8:$D$307,Amortissement_prêt!$A$8:$A$307,">"&(A20-1)*12,Amortissement_prêt!$A$8:$A$307,"<="&A20*12) -> 7228.7029 | D20: =SUMIFS(Amortissement_prêt!$E$8:$E$307,Amortissement_prêt!$A$8:$A$307,">"&(A20-1)*12,Amortissement_prêt!$A$8:$A$307,"<="&A20*12) -> 20784.158 | E20: =SUMIFS(Amortissement_prêt!$G$8:$G$307,Amortissement_prêt!$A$8:$A$307,">"&(A20-1)*12,Amortissement_prêt!$A$8:$A$307,"<="&A20*12) -> 309.80155 | F20: =C20+D20+E20 -> 28322.663
... A33: 25 | B33: {=INDEX(Amortissement_prêt!$F$8:$F$307,A33*12)} -> 6.5028871e-11 | C33: =SUMIFS(Amortissement_prêt!$D$8:$D$307,Amortissement_prêt!$A$8:$A$307,">"&(A33-1)*12,Amortissement_prêt!$A$8:$A$307,"<="&A33*12) -> 2.2760105e-12 | D33: =SUMIFS(Amortissement_prêt!$E$8:$E$307,Amortissement_prêt!$A$8:$A$307,">"&(A33-1)*12,Amortissement_prêt!$A$8:$A$307,"<="&A33*12) -> 0 | E33: =SUMIFS(Amortissement_prêt!$G$8:$G$307,Amortissement_prêt!$A$8:$A$307,">"&(A33-1)*12,Amortissement_prêt!$A$8:$A$307,"<="&A33*12) -> 0 | F33: =C33+D33+E33 -> 2.2760105e-12

Sheet FLux_Achat_RP
A1: Année | B1: Valeur du bien | C1: CRD fin d'année | D1: Charges copro | E1: Taxe foncière | F1: Intérêts+Capital+Assurance | G1: Charges annuelles totales | H1: Total déboursé annuel | I1: Patrimoine net immobilier
A2: 0 | B2: =Projet!$C$12 -> 500000
A3: 1 | B3: =$B$2*(1+Projet!$C$22)^A3 -> 505000 | C3: {=IF(A3>25,0,INDEX(Amortissement_annuel_prêt!$B$9:$B$33,A3))} -> 388361.07 | D3: =Projet!$C$20*(1+Projet!$C$24)^(A3-1) -> 1500 | E3: =Projet!$C$21*(1+Projet!$C$23)^(A3-1) -> 1500 | F3: {=IF(A3>25,0,INDEX(Amortissement_annuel_prêt!$F$9:$F$33,A3))} -> 28606.961 | G3: =D3+E3 -> 3000 | H3: =F3+G3 -> 31606.961 | I3: =B3-C3 -> 116638.93
A4: 2 | B4: =$B$2*(1+Projet!$C$22)^A4 -> 510050 | C4: {=IF(A4>25,0,INDEX(Amortissement_annuel_prêt!$B$9:$B$33,A4))} -> 373707.26 | D4: =Projet!$C$20*(1+Projet!$C$24)^(A4-1) -> 1515 | E4: =Projet!$C$21*(1+Projet!$C$23)^(A4-1) -> 1515 | F4: {=IF(A4>25,0,INDEX(Amortissement_annuel_prêt!$F$9:$F$33,A4))} -> 28585.392 | G4: =D4+E4 -> 3030 | H4: =F4+G4 -> 31615.392 | I4: =B4-C4 -> 136342.74
A5: 3 | B5: =$B$2*(1+Projet!$C$22)^A5 -> 515150.5 | C5: {=IF(A5>25,0,INDEX(Amortissement_annuel_prêt!$B$9:$B$33,A5))} -> 358532.25 | D5: =Projet!$C$20*(1+Projet!$C$24)^(A5-1) -> 1530.15 | E5: =Projet!$C$21*(1+Projet!$C$23)^(A5-1) -> 1530.15 | F5: {=IF(A5>25,0,INDEX(Amortissement_annuel_prêt!$F$9:$F$33,A5))} -> 28563.055 | G5: =D5+E5 -> 3060.3 | H5: =F5+G5 -> 31623.355 | I5: =B5-C5 -> 156618.25
A6: 4 | B6: =$B$2*(1+Projet!$C$22)^A6 -> 520302.01 | C6: {=IF(A6>25,0,INDEX(Amortissement_annuel_prêt!$B$9:$B$33,A6))} -> 342817.52 | D6: =Projet!$C$20*(1+Projet!$C$24)^(A6-1) -> 1545.4515 | E6: =Projet!$C$21*(1+Projet!$C$23)^(A6-1) -> 1545.4515 | F6: {=IF(A6>25,0,INDEX(Amortissement_annuel_prêt!$F$9:$F$33,A6))} -> 28539.924 | G6: =D6+E6 -> 3090.903 | H6: =F6+G6 -> 31630.827 | I6: =B6-C6 -> 177484.48
A7: 5 | B7: =$B$2*(1+Projet!$C$22)^A7 -> 525505.03 | C7: {=IF(A7>25,0,INDEX(Amortissement_annuel_prêt!$B$9:$B$33,A7))} -> 326543.87 | D7: =Projet!$C$20*(1+Projet!$C$24)^(A7-1) -> 1560.906 | E7: =Projet!$C$21*(1+Projet!$C$23)^(A7-1) -> 1560.906 | F7: {=IF(A7>25,0,INDEX(Amortissement_annuel_prêt!$F$9:$F$33,A7))} -> 28515.97 | G7: =D7+E7 -> 3121.812 | H7: =F7+G7 -> 31637.782 | I7: =B7-C7 -> 198961.16
A8: 6 | B8: =$B$2*(1+Projet!$C$22)^A8 -> 530760.08 | C8: {=IF(A8>25,0,INDEX(Amortissement_annuel_prêt!$B$9:$B$33,A8))} -> 309691.4 | D8: =Projet!$C$20*(1+Projet!$C$24)^(A8-1) -> 1576.5151 | E8: =Projet!$C$21*(1+Projet!$C$23)^(A8-1) -> 1576.5151 | F8: {=IF(A8>25,0,INDEX(Amortissement_annuel_prêt!$F$9:$F$33,A8))} -> 28491.164 | G8: =D8+E8 -> 3153.0302 | H8: =F8+G8 -> 31644.194 | I8: =B8-C8 -> 221068.67
A9: 7 | B9: =$B$2*(1+Projet!$C$22)^A9 -> 536067.68 | C9: {=IF(A9>25,0,INDEX(Amortissement_annuel_prêt!$B$9:$B$33,A9))} -> 292239.55 | D9: =Projet!$C$20*(1+Projet!$C$24)^(A9-1) -> 1592.2802 | E9: =Projet!$C$21*(1+Projet!$C$23)^(A9-1) -> 1592.2802 | F9: {=IF(A9>25,0,INDEX(Amortissement_annuel_prêt!$F$9:$F$33,A9))} -> 28465.476 | G9: =D9+E9 -> 3184.5605 | H9: =F9+G9 -> 31650.036 | I9: =B9-C9 -> 243828.12
A10: 8 | B10: =$B$2*(1+Projet!$C$22)^A10 -> 541428.35 | C10: {=IF(A10>25,0,INDEX(Amortissement_annuel_prêt!$B$9:$B$33,A10))} -> 274166.99 | D10: =Projet!$C$20*(1+Projet!$C$24)^(A10-1) -> 1608.203 | E10: =Projet!$C$21*(1+Projet!$C$23)^(A10-1) -> 1608.203 | F10: {=IF(A10>25,0,INDEX(Amortissement_annuel_prêt!$F$9:$F$33,A10))} -> 28438.874 | G10: =D10+E10 -> 3216.4061 | H10: =F10+G10 -> 31655.28 | I10: =B10-C10 -> 267261.36
A11: 9 | B11: =$B$2*(1+Projet!$C$22)^A11 -> 546842.64 | C11: {=IF(A11>25,0,INDEX(Amortissement_annuel_prêt!$B$9:$B$33,A11))} -> 255451.64 | D11: =Projet!$C$20*(1+Projet!$C$24)^(A11-1) -> 1624.2851 | E11: =Projet!$C$21*(1+Projet!$C$23)^(A11-1) -> 1624.2851 | F11: {=IF(A11>25,0,INDEX(Amortissement_annuel_prêt!$F$9:$F$33,A11))} -> 28411.326 | G11: =D11+E11 -> 3248.5701 | H11: =F11+G11 -> 31659.896 | I11: =B11-C11 -> 291390.99
A12: 10 | B12: =$B$2*(1+Projet!$C$22)^A12 -> 552311.06 | C12: {=IF(A12>25,0,INDEX(Amortissement_annuel_prêt!$B$9:$B$33,A12))} -> 236070.65 | D12: =Projet!$C$20*(1+Projet!$C$24)^(A12-1) -> 1640.5279 | E12: =Projet!$C$21*(1+Projet!$C$23)^(A12-1) -> 1640.5279 | F12: {=IF(A12>25,0,INDEX(Amortissement_annuel_prêt!$F$9:$F$33,A12))} -> 28382.798 | G12: =D12+E12 -> 3281.0558 | H12: =F12+G12 -> 31663.854 | I12: =B12-C12 -> 316240.41
A13: 11 | B13: =$B$2*(1+Projet!$C$22)^A13 -> 557834.17 | C13: {=IF(A13>25,0,INDEX(Amortissement_annuel_prêt!$B$9:$B$33,A13))} -> 216000.33 | D13: =Projet!$C$20*(1+Projet!$C$24)^(A13-1) -> 1656.9332 | E13: =Projet!$C$21*(1+Projet!$C$23)^(A13-1) -> 1656.9332 | F13: {=IF(A13>25,0,INDEX(Amortissement_annuel_prêt!$F$9:$F$33,A13))} -> 28353.256 | G13: =D13+E13 -> 3313.8664 | H13: =F13+G13 -> 31667.122 | I13: =B13-C13 -> 341833.84
A14: 12 | B14: =$B$2*(1+Projet!$C$22)^A14 -> 563412.52 | C14: {=IF(A14>25,0,INDEX(Amortissement_annuel_prêt!$B$9:$B$33,A14))} -> 195216.17 | D14: =Projet!$C$20*(1+Projet!$C$24)^(A14-1) -> 1673.5025 | E14: =Projet!$C$21*(1+Projet!$C$23)^(A14-1) -> 1673.5025 | F14: {=IF(A14>25,0,INDEX(Amortissement_annuel_prêt!$F$9:$F$33,A14))} -> 28322.663 | G14: =D14+E14 -> 3347.005 | H14: =F14+G14 -> 31669.668 | I14: =B14-C14 -> 368196.34
... A27: 25 | B27: =$B$2*(1+Projet!$C$22)^A27 -> 641216 | C27: {=IF(A27>25,0,INDEX(Amortissement_annuel_prêt!$B$9:$B$33,A27))} -> 6.5028871e-11 | D27: =Projet!$C$20*(1+Projet!$C$24)^(A27-1) -> 1904.602 | E27: =Projet!$C$21*(1+Projet!$C$23)^(A27-1) -> 1904.602 | F27: {=IF(A27>25,0,INDEX(Amortissement_annuel_prêt!$F$9:$F$33,A27))} -> 2.2760105e-12 | G27: =D27+E27 -> 3809.2039 | H27: =F27+G27 -> 3809.2039 | I27: =B27-C27 -> 641216

Sheet Bilan_Revente
A1: Frais de revente | B1: 0
B2: ACHAT | O2: LOCATION | W2: COMPARATIF
A3: Année | B3: Patrimoine net immobilier | C3: Cash net si revente | D3: Cumul décaissé depuis achat | E3: Gain/Perte cash pur | F3: Aide | G3: Surplus propriétaire | H3: Capital début (proprio) | I3: Rendement | J3: Capital avant versement | K3: Capital après versement | L3: Impôt latent achat | M3: Capital net d'impôt achat | N3: Patrimoine total achat | O3: Loyer annuel | P3: Surplus locataire investi | Q3: Capital début année | R3: Rendement | S3: Capital avant versement | T3: Capital après versement | U3: Impôt latent location | V3: Capital net d'impôt location | W3: Ecart achat vs location
A4: =FLux_Achat_RP!A3 -> 1 | B4: =FLux_Achat_RP!I3 -> 116638.93 | C4: =B4-$B$1 -> 116638.93 | D4: =Projet!$C$14+FLux_Achat_RP!H3 -> 131606.96 | E4: =C4-D4 -> -14968.03 | F4: =IF(E4>=0,A4,"") | G4: =MAX(Projet!$C$3*12-FLux_Achat_RP!H3,0) -> 9193.0387 | H4: =Projet!$C$2-Projet!$C$14 -> 100000 | I4: =H4*Projet!$C$28 -> 5000 | J4: =H4+I4 -> 105000 | K4: =J4+G4 -> 114193.04 | L4: =MAX(K4-(Projet!$C$2-Projet!$C$14+SUM($G$4:G4)),0)*Projet!$C$29 -> 1570 | M4: =K4-L4 -> 112623.04 | N4: =B4+M4 -> 229261.97 | O4: =Projet!$C$26*12*(1+Projet!$C$27)^(A4-1) -> 19200 | P4: =MAX(Projet!$C$3*12-O4,0) -> 21600 | Q4: =Projet!$C$2 -> 200000 | R4: =Q4*Projet!$C$28 -> 10000 | S4: =Q4+R4 -> 210000 | T4: =S4+P4 -> 231600 | U4: =MAX(T4-(Projet!$C$2+SUM($P$4:P4)),0)*Projet!$C$29 -> 3140 | V4: =T4-U4 -> 228460 | W4: =N4-V4 -> 801.96962
A5: =FLux_Achat_RP!A4 -> 2 | B5: =FLux_Achat_RP!I4 -> 136342.74 | C5: =B5-$B$1 -> 136342.74 | D5: =D4+FLux_Achat_RP!H4 -> 163222.35 | E5: =C5-D5 -> -26879.61 | F5: =IF(E5>=0,A5,"") | G5: =MAX(Projet!$C$3*12-FLux_Achat_RP!H4,0) -> 9184.6083 | H5: =K4 -> 114193.04 | I5: =H5*Projet!$C$28 -> 5709.6519 | J5: =H5+I5 -> 119902.69 | K5: =J5+G5 -> 129087.3 | L5: =MAX(K5-(Projet!$C$2-Projet!$C$14+SUM($G$4:G5)),0)*Projet!$C$29 -> 3362.8307 | M5: =K5-L5 -> 125724.47 | N5: =B5+M5 -> 262067.21 | O5: =Projet!$C$26*12*(1+Projet!$C$27)^(A5-1) -> 19392 | P5: =MAX(Projet!$C$3*12-O5,0) -> 21408 | Q5: =T4 -> 231600 | R5: =Q5*Projet!$C$28 -> 11580 | S5: =Q5+R5 -> 243180 | T5: =S5+P5 -> 264588 | U5: =MAX(T5-(Projet!$C$2+SUM($P$4:P5)),0)*Projet!$C$29 -> 6776.12 | V5: =T5-U5 -> 257811.88 | W5: =N5-V5 -> 4255.331
A6: =FLux_Achat_RP!A5 -> 3 | B6: =FLux_Achat_RP!I5 -> 156618.25 | C6: =B6-$B$1 -> 156618.25 | D6: =D5+FLux_Achat_RP!H5 -> 194845.71 | E6: =C6-D6 -> -38227.462 | F6: =IF(E6>=0,A6,"") | G6: =MAX(Projet!$C$3*12-FLux_Achat_RP!H5,0) -> 9176.6451 | H6: =K5 -> 129087.3 | I6: =H6*Projet!$C$28 -> 6454.3649 | J6: =H6+I6 -> 135541.66 | K6: =J6+G6 -> 144718.31 | L6: =MAX(K6-(Projet!$C$2-Projet!$C$14+SUM($G$4:G6)),0)*Projet!$C$29 -> 5389.5013 | M6: =K6-L6 -> 139328.81 | N6: =B6+M6 -> 295947.05 | O6: =Projet!$C$26*12*(1+Projet!$C$27)^(A6-1) -> 19585.92 | P6: =MAX(Projet!$C$3*12-O6,0) -> 21214.08 | Q6: =T5 -> 264588 | R6: =Q6*Projet!$C$28 -> 13229.4 | S6: =Q6+R6 -> 277817.4 | T6: =S6+P6 -> 299031.48 | U6: =MAX(T6-(Projet!$C$2+SUM($P$4:P6)),0)*Projet!$C$29 -> 10930.152 | V6: =T6-U6 -> 288101.33 | W6: =N6-V6 -> 7845.7253
A7: =FLux_Achat_RP!A6 -> 4 | B7: =FLux_Achat_RP!I6 -> 177484.48 | C7: =B7-$B$1 -> 177484.48 | D7: =D6+FLux_Achat_RP!H6 -> 226476.53 | E7: =C7-D7 -> -48992.052 | F7: =IF(E7>=0,A7,"") | G7: =MAX(Projet!$C$3*12-FLux_Achat_RP!H6,0) -> 9169.1733 | H7: =K6 -> 144718.31 | I7: =H7*Projet!$C$28 -> 7235.9155 | J7: =H7+I7 -> 151954.22 | K7: =J7+G7 -> 161123.4 | L7: =MAX(K7-(Projet!$C$2-Projet!$C$14+SUM($G$4:G7)),0)*Projet!$C$29 -> 7661.5788 | M7: =K7-L7 -> 153461.82 | N7: =B7+M7 -> 330946.3 | O7: =Projet!$C$26*12*(1+Projet!$C$27)^(A7-1) -> 19781.779 | P7: =MAX(Projet!$C$3*12-O7,0) -> 21018.221 | Q7: =T6 -> 299031.48 | R7: =Q7*Projet!$C$28 -> 14951.574 | S7: =Q7+R7 -> 313983.05 | T7: =S7+P7 -> 335001.27 | U7: =MAX(T7-(Projet!$C$2+SUM($P$4:P7)),0)*Projet!$C$29 -> 15624.946 | V7: =T7-U7 -> 319376.33 | W7: =N7-V7 -> 11569.973
A8: =FLux_Achat_RP!A7 -> 5 | B8: =FLux_Achat_RP!I7 -> 198961.16 | C8: =B8-$B$1 -> 198961.16 | D8: =D7+FLux_Achat_RP!H7 -> 258114.32 | E8: =C8-D8 -> -59153.156 | F8: =IF(E8>=0,A8,"") | G8: =MAX(Projet!$C$3*12-FLux_Achat_RP!H7,0) -> 9162.2182 | H8: =K7 -> 161123.4 | I8: =H8*Projet!$C$28 -> 8056.1699 | J8: =H8+I8 -> 169179.57 | K8: =J8+G8 -> 178341.79 | L8: =MAX(K8-(Projet!$C$2-Projet!$C$14+SUM($G$4:G8)),0)*Projet!$C$29 -> 10191.216 | M8: =K8-L8 -> 168150.57 | N8: =B8+M8 -> 367111.73 | O8: =Projet!$C$26*12*(1+Projet!$C$27)^(A8-1) -> 19979.597 | P8: =MAX(Projet!$C$3*12-O8,0) -> 20820.403 | Q8: =T7 -> 335001.27 | R8: =Q8*Projet!$C$28 -> 16750.064 | S8: =Q8+R8 -> 351751.34 | T8: =S8+P8 -> 372571.74 | U8: =MAX(T8-(Projet!$C$2+SUM($P$4:P8)),0)*Projet!$C$29 -> 20884.466 | V8: =T8-U8 -> 351687.28 | W8: =N8-V8 -> 15424.454
A9: =FLux_Achat_RP!A8 -> 6 | B9: =FLux_Achat_RP!I8 -> 221068.67 | C9: =B9-$B$1 -> 221068.67 | D9: =D8+FLux_Achat_RP!H8 -> 289758.51 | E9: =C9-D9 -> -68689.839 | F9: =IF(E9>=0,A9,"") | G9: =MAX(Projet!$C$3*12-FLux_Achat_RP!H8,0) -> 9155.806 | H9: =K8 -> 178341.79 | I9: =H9*Projet!$C$28 -> 8917.0893 | J9: =H9+I9 -> 187258.88 | K9: =J9+G9 -> 196414.68 | L9: =MAX(K9-(Projet!$C$2-Projet!$C$14+SUM($G$4:G9)),0)*Projet!$C$29 -> 12991.182 | M9: =K9-L9 -> 183423.5 | N9: =B9+M9 -> 404492.17 | O9: =Projet!$C$26*12*(1+Projet!$C$27)^(A9-1) -> 20179.393 | P9: =MAX(Projet!$C$3*12-O9,0) -> 20620.607 | Q9: =T8 -> 372571.74 | R9: =Q9*Projet!$C$28 -> 18628.587 | S9: =Q9+R9 -> 391200.33 | T9: =S9+P9 -> 411820.94 | U9: =MAX(T9-(Projet!$C$2+SUM($P$4:P9)),0)*Projet!$C$29 -> 26733.842 | V9: =T9-U9 -> 385087.09 | W9: =N9-V9 -> 19405.077
A10: =FLux_Achat_RP!A9 -> 7 | B10: =FLux_Achat_RP!I9 -> 243828.12 | C10: =B10-$B$1 -> 243828.12 | D10: =D9+FLux_Achat_RP!H9 -> 321408.55 | E10: =C10-D10 -> -77580.422 | F10: =IF(E10>=0,A10,"") | G10: =MAX(Projet!$C$3*12-FLux_Achat_RP!H9,0) -> 9149.9639 | H10: =K9 -> 196414.68 | I10: =H10*Projet!$C$28 -> 9820.7341 | J10: =H10+I10 -> 206235.42 | K10: =J10+G10 -> 215385.38 | L10: =MAX(K10-(Projet!$C$2-Projet!$C$14+SUM($G$4:G10)),0)*Projet!$C$29 -> 16074.893 | M10: =K10-L10 -> 199310.49 | N10: =B10+M10 -> 443138.61 | O10: =Projet!$C$26*12*(1+Projet!$C$27)^(A10-1) -> 20381.187 | P10: =MAX(Projet!$C$3*12-O10,0) -> 20418.813 | Q10: =T9 -> 411820.94 | R10: =Q10*Projet!$C$28 -> 20591.047 | S10: =Q10+R10 -> 432411.98 | T10: =S10+P10 -> 452830.8 | U10: =MAX(T10-(Projet!$C$2+SUM($P$4:P10)),0)*Projet!$C$29 -> 33199.431 | V10: =T10-U10 -> 419631.36 | W10: =N10-V10 -> 23507.246
A11: =FLux_Achat_RP!A10 -> 8 | B11: =FLux_Achat_RP!I10 -> 267261.36 | C11: =B11-$B$1 -> 267261.36 | D11: =D10+FLux_Achat_RP!H10 -> 353063.83 | E11: =C11-D11 -> -85802.464 | F11: =IF(E11>=0,A11,"") | G11: =MAX(Projet!$C$3*12-FLux_Achat_RP!H10,0) -> 9144.7201 | H11: =K10 -> 215385.38 | I11: =H11*Projet!$C$28 -> 10769.269 | J11: =H11+I11 -> 226154.65 | K11: =J11+G11 -> 235299.37 | L11: =MAX(K11-(Projet!$C$2-Projet!$C$14+SUM($G$4:G11)),0)*Projet!$C$29 -> 19456.443 | M11: =K11-L11 -> 215842.93 | N11: =B11+M11 -> 483104.29 | O11: =Projet!$C$26*12*(1+Projet!$C$27)^(A11-1) -> 20584.999 | P11: =MAX(Projet!$C$3*12-O11,0) -> 20215.001 | Q11: =T10 -> 452830.8 | R11: =Q11*Projet!$C$28 -> 22641.54 | S11: =Q11+R11 -> 475472.34 | T11: =S11+P11 -> 495687.34 | U11: =MAX(T11-(Projet!$C$2+SUM($P$4:P11)),0)*Projet!$C$29 -> 40308.874 | V11: =T11-U11 -> 455378.46 | W11: =N11-V11 -> 27725.825
A12: =FLux_Achat_RP!A11 -> 9 | B12: =FLux_Achat_RP!I11 -> 291390.99 | C12: =B12-$B$1 -> 291390.99 | D12: =D11+FLux_Achat_RP!H11 -> 384723.72 | E12: =C12-D12 -> -93332.729 | F12: =IF(E12>=0,A12,"") | G12: =MAX(Projet!$C$3*12-FLux_Achat_RP!H11,0) -> 9140.104 | H12: =K11 -> 235299.37 | I12: =H12*Projet!$C$28 -> 11764.968 | J12: =H12+I12 -> 247064.34 | K12: =J12+G12 -> 256204.44 | L12: =MAX(K12-(Projet!$C$2-Projet!$C$14+SUM($G$4:G12)),0)*Projet!$C$29 -> 23150.643 | M12: =K12-L12 -> 233053.8 | N12: =B12+M12 -> 524444.79 | O12: =Projet!$C$26*12*(1+Projet!$C$27)^(A12-1) -> 20790.849 | P12: =MAX(Projet!$C$3*12-O12,0) -> 20009.151 | Q12: =T11 -> 495687.34 | R12: =Q12*Projet!$C$28 -> 24784.367 | S12: =Q12+R12 -> 520471.7 | T12: =S12+P12 -> 540480.85 | U12: =MAX(T12-(Projet!$C$2+SUM($P$4:P12)),0)*Projet!$C$29 -> 48091.166 | V12: =T12-U12 -> 492389.69 | W12: =N12-V12 -> 32055.102
A13: =FLux_Achat_RP!A12 -> 10 | B13: =FLux_Achat_RP!I12 -> 316240.41 | C13: =B13-$B$1 -> 316240.41 | D13: =D12+FLux_Achat_RP!H12 -> 416387.58 | E13: =C13-D13 -> -100147.16 | F13: =IF(E13>=0,A13,"") | G13: =MAX(Projet!$C$3*12-FLux_Achat_RP!H12,0) -> 9136.1461 | H13: =K12 -> 256204.44 | I13: =H13*Projet!$C$28 -> 12810.222 | J13: =H13+I13 -> 269014.66 | K13: =J13+G13 -> 278150.81 | L13: =MAX(K13-(Projet!$C$2-Projet!$C$14+SUM($G$4:G13)),0)*Projet!$C$29 -> 27173.053 | M13: =K13-L13 -> 250977.76 | N13: =B13+M13 -> 567218.17 | O13: =Projet!$C$26*12*(1+Projet!$C$27)^(A13-1) -> 20998.757 | P13: =MAX(Projet!$C$3*12-O13,0) -> 19801.243 | Q13: =T12 -> 540480.85 | R13: =Q13*Projet!$C$28 -> 27024.043 | S13: =Q13+R13 -> 567504.9 | T13: =S13+P13 -> 587306.14 | U13: =MAX(T13-(Projet!$C$2+SUM($P$4:P13)),0)*Projet!$C$29 -> 56576.715 | V13: =T13-U13 -> 530729.43 | W13: =N13-V13 -> 36488.745
A14: =FLux_Achat_RP!A13 -> 11 | B14: =FLux_Achat_RP!I13 -> 341833.84 | C14: =B14-$B$1 -> 341833.84 | D14: =D13+FLux_Achat_RP!H13 -> 448054.7 | E14: =C14-D14 -> -106220.85 | F14: =IF(E14>=0,A14,"") | G14: =MAX(Projet!$C$3*12-FLux_Achat_RP!H13,0) -> 9132.8779 | H14: =K13 -> 278150.81 | I14: =H14*Projet!$C$28 -> 13907.54 | J14: =H14+I14 -> 292058.35 | K14: =J14+G14 -> 301191.23 | L14: =MAX(K14-(Projet!$C$2-Projet!$C$14+SUM($G$4:G14)),0)*Projet!$C$29 -> 31540.021 | M14: =K14-L14 -> 269651.21 | N14: =B14+M14 -> 611485.05 | O14: =Projet!$C$26*12*(1+Projet!$C$27)^(A14-1) -> 21208.745 | P14: =MAX(Projet!$C$3*12-O14,0) -> 19591.255 | Q14: =T13 -> 587306.14 | R14: =Q14*Projet!$C$28 -> 29365.307 | S14: =Q14+R14 -> 616671.45 | T14: =S14+P14 -> 636262.7 | U14: =MAX(T14-(Projet!$C$2+SUM($P$4:P14)),0)*Projet!$C$29 -> 65797.421 | V14: =T14-U14 -> 570465.28 | W14: =N14-V14 -> 41019.769
A15: =FLux_Achat_RP!A14 -> 12 | B15: =FLux_Achat_RP!I14 -> 368196.34 | C15: =B15-$B$1 -> 368196.34 | D15: =D14+FLux_Achat_RP!H14 -> 479724.37 | E15: =C15-D15 -> -111528.02 | F15: =IF(E15>=0,A15,"") | G15: =MAX(Projet!$C$3*12-FLux_Achat_RP!H14,0) -> 9130.3324 | H15: =K14 -> 301191.23 | I15: =H15*Projet!$C$28 -> 15059.561 | J15: =H15+I15 -> 316250.79 | K15: =J15+G15 -> 325381.12 | L15: =MAX(K15-(Projet!$C$2-Projet!$C$14+SUM($G$4:G15)),0)*Projet!$C$29 -> 36268.723 | M15: =K15-L15 -> 289112.4 | N15: =B15+M15 -> 657308.74 | O15: =Projet!$C$26*12*(1+Projet!$C$27)^(A15-1) -> 21420.832 | P15: =MAX(Projet!$C$3*12-O15,0) -> 19379.168 | Q15: =T14 -> 636262.7 | R15: =Q15*Projet!$C$28 -> 31813.135 | S15: =Q15+R15 -> 668075.84 | T15: =S15+P15 -> 687455.01 | U15: =MAX(T15-(Projet!$C$2+SUM($P$4:P15)),0)*Projet!$C$29 -> 75786.746 | V15: =T15-U15 -> 611668.26 | W15: =N15-V15 -> 45640.482
A16: =FLux_Achat_RP!A15 -> 13 | B16: =FLux_Achat_RP!I15 -> 395353.86 | C16: =B16-$B$1 -> 395353.86 | D16: =D15+FLux_Achat_RP!H15 -> 511395.82 | E16: =C16-D16 -> -116041.97 | F16: =IF(E16>=0,A16,"") | G16: =MAX(Projet!$C$3*12-FLux_Achat_RP!H15,0) -> 9128.5436 | H16: =K15 -> 325381.12 | I16: =H16*Projet!$C$28 -> 16269.056 | J16: =H16+I16 -> 341650.18 | K16: =J16+G16 -> 350778.72 | L16: =MAX(K16-(Projet!$C$2-Projet!$C$14+SUM($G$4:G16)),0)*Projet!$C$29 -> 41377.206 | M16: =K16-L16 -> 309401.51 | N16: =B16+M16 -> 704755.37 | O16: =Projet!$C$26*12*(1+Projet!$C$27)^(A16-1) -> 21635.041 | P16: =MAX(Projet!$C$3*12-O16,0) -> 19164.959 | Q16: =T15 -> 687455.01 | R16: =Q16*Projet!$C$28 -> 34372.75 | S16: =Q16+R16 -> 721827.76 | T16: =S16+P16 -> 740992.71 | U16: =MAX(T16-(Projet!$C$2+SUM($P$4:P16)),0)*Projet!$C$29 -> 86579.789 | V16: =T16-U16 -> 654412.93 | W16: =N16-V16 -> 50342.444
... A28: =FLux_Achat_RP!A27 -> 25 | B28: =FLux_Achat_RP!I27 -> 641216 | C28: =B28-$B$1 -> 641216 | D28: =D27+FLux_Achat_RP!H27 -> 751747.35 | E28: =C28-D28 -> -110531.35 | F28: =IF(E28>=0,A28,"") | G28: =MAX(Projet!$C$3*12-FLux_Achat_RP!H27,0) -> 36990.796 | H28: =K27 -> 850165.85 | I28: =H28*Projet!$C$28 -> 42508.292 | J28: =H28+I28 -> 892674.14 | K28: =J28+G28 -> 929664.94 | L28: =MAX(K28-(Projet!$C$2-Projet!$C$14+SUM($G$4:G28)),0)*Projet!$C$29 -> 144883.46 | M28: =K28-L28 -> 784781.48 | N28: =B28+M28 -> 1425997.5 | O28: =Projet!$C$26*12*(1+Projet!$C$27)^(A28-1) -> 24378.905 | P28: =MAX(Projet!$C$3*12-O28,0) -> 16421.095 | Q28: =T27 -> 1522126.2 | R28: =Q28*Projet!$C$28 -> 76106.31 | S28: =Q28+R28 -> 1598232.5 | T28: =S28+P28 -> 1614653.6 | U28: =MAX(T28-(Projet!$C$2+SUM($P$4:P28)),0)*Projet!$C$29 -> 294193.83 | V28: =T28-U28 -> 1320459.8 | W28: =N28-V28 -> 105537.71
